build1101/__init__.py
build1101/cli.py
build1101-0.0.3.dist-info/METADATA
build1101-0.0.3.dist-info/WHEEL
build1101-0.0.3.dist-info/entry_points.txt
build1101-0.0.3.dist-info/top_level.txt
build1101-0.0.3.dist-info/RECORD
